Flashflood-0.13.0.dist-info/DESCRIPTION.rst
Flashflood-0.13.0.dist-info/METADATA
Flashflood-0.13.0.dist-info/RECORD
Flashflood-0.13.0.dist-info/WHEEL
Flashflood-0.13.0.dist-info/metadata.json
Flashflood-0.13.0.dist-info/top_level.txt
flashflood/__init__.py
flashflood/auth.py
flashflood/debug.py
flashflood/functional.py
flashflood/graph.py
flashflood/legacy.py
flashflood/lod.py
flashflood/sort.py
flashflood/static.py
flashflood/core/__init__.py
flashflood/core/concurrent.py
flashflood/core/container.py
flashflood/core/edge.py
flashflood/core/jobqueue.py
flashflood/core/node.py
flashflood/core/task.py
flashflood/core/workflow.py
flashflood/interface/__init__.py
flashflood/interface/sqlite.py
flashflood/interface/xlsx.py
flashflood/node/__init__.py
flashflood/node/aggregate/__init__.py
flashflood/node/aggregate/first.py
flashflood/node/aggregate/list.py
flashflood/node/aggregate/sum.py
flashflood/node/aggregate/uniqlist.py
flashflood/node/aggregate/update.py
flashflood/node/chem/__init__.py
flashflood/node/chem/descriptor.py
flashflood/node/chem/molecule.py
flashflood/node/control/__init__.py
flashflood/node/control/filter.py
flashflood/node/control/replicate.py
flashflood/node/field/__init__.py
flashflood/node/field/concat.py
flashflood/node/field/constant.py
flashflood/node/field/extend.py
flashflood/node/field/extract.py
flashflood/node/field/number.py
flashflood/node/field/remove.py
flashflood/node/field/split.py
flashflood/node/field/update.py
flashflood/node/monitor/__init__.py
flashflood/node/monitor/count.py
flashflood/node/monitor/stdout.py
flashflood/node/reader/__init__.py
flashflood/node/reader/csv.py
flashflood/node/reader/httpfetch.py
flashflood/node/reader/iterinput.py
flashflood/node/reader/readerbase.py
flashflood/node/reader/sdfile.py
flashflood/node/reader/sqlite.py
flashflood/node/record/__init__.py
flashflood/node/record/excludes.py
flashflood/node/record/filter.py
flashflood/node/record/includes.py
flashflood/node/record/merge.py
flashflood/node/record/numericfilter.py
flashflood/node/record/sort.py
flashflood/node/record/startswith.py
flashflood/node/transform/__init__.py
flashflood/node/transform/combination.py
