Metadata-Version: 2.0
Name: Flashflood
Version: 0.13.0
Summary: HTTP API server builder for chemical database workflow
Home-page: https://github.com/mojaie/flashflood
Author: Seiji Matsuoka
Author-email: mojaie@aol.com
License: MIT
Keywords: drug-discovery cheminformatics api-server workflow
Platform: UNKNOWN
Classifier: Development Status :: 3 - Alpha
Classifier: Intended Audience :: Science/Research
Classifier: Topic :: Scientific/Engineering :: Chemistry
Classifier: Topic :: Scientific/Engineering :: Bio-Informatics
Classifier: License :: OSI Approved :: MIT License
Classifier: Programming Language :: Python
Classifier: Programming Language :: Python :: 3.5
Classifier: Programming Language :: Python :: 3.6
Requires-Python: >=3.6
Requires-Dist: chorus
Requires-Dist: tornado
Requires-Dist: xlsxwriter
